<object clone="/usr/SkotOS/obj/verb" owner="TextIF">
  <Socials:Verb imp="lock" second="lock" third="locks" evoke="optional" audible="false" private="false" secret="false" obscured="false" target-abstracts="false" disabled="false" ooc="false" raw_verb="false">
    <Ur:UrObject/>
    <Socials:SocialObjects>
      <Socials:SocialObject role="iob" direct="false" single="false" raw="false" requirement="optional" distance="far">
        <Socials:SocObPreps>
          <Socials:SocObPrep prep="on"/>
        </Socials:SocObPreps>
        <Socials:SocObFilters/>
      </Socials:SocialObject>
      <Socials:SocialObject role="using" direct="false" single="false" raw="false" requirement="optional" distance="owned">
        <Socials:SocObPreps>
          <Socials:SocObPrep prep="with"/>
          <Socials:SocObPrep prep="using"/>
          <Socials:SocObPrep prep="on"/>
        </Socials:SocObPreps>
        <Socials:SocObFilters/>
      </Socials:SocialObject>
      <Socials:SocialObject role="what" direct="true" single="true" raw="false" requirement="required" distance="close">
        <Socials:SocObPreps/>
        <Socials:SocObFilters/>
      </Socials:SocialObject>
    </Socials:SocialObjects>
    <Socials:VerbActions/>
    <Core:Properties>
      <Core:Property property="revisions">
         (\{ 1135371871, "-", "SYNC", 1453936810, "rorschakovacs", "X", 1453936827, "rorschakovacs", "E", 1597106569, "jominey", "E", 1597106577, "jominey", "E", 1597106579, "jominey", "E", 1597106586, "jominey", "E", 1597106591, "jominey", "E", 1597106613, "jominey", "E", 1597106616, "jominey", "E", 1597106618, "jominey", "E", 1597106634, "jominey", "E" \})
      </Core:Property>
      <Core:Property property="sys:sync:clearing">1</Core:Property>
      <Core:Property property="sys:sync:idpsource">
         "ironclaw"
      </Core:Property>
      <Core:Property property="sys:sync:igdipro">
         "propose"
      </Core:Property>
      <Core:Property property="sys:sync:proposing-revision">
         1135371871
      </Core:Property>
    </Core:Properties>
    <Notes:Notes/>
  </Socials:Verb>
</object>
