<object clone="/base/obj/thing" owner="zwoc">
  <Base:Thing>
    <Ur:UrObject/>
    <Base:Bulk immobile="false" mass="1" density="1"/>
    <Base:Container flexible="false" transparent-container="false" public-container="false" tight="false" capacity="1" maxweight="1"/>
    <Base:Misc gender="neuter" volition="false" weapon="false" default_stance="none" combinable="false" discrete="false" by_weight="false" tight="false" scriptrunner="false">
      <Base:Edible value="false"/>
      <Base:Potable value="false"/>
      <Base:DrinkMessageFirst/>
      <Base:DrinkMessageThird/>
      <Base:Transparency value="false"/>
      <Base:Unsafe value="false"/>
      <Base:Safe value="false"/>
      <Base:ClothesExpected value="false"/>
      <Base:DieMessageFirst/>
      <Base:DieMessageThird/>
    </Base:Misc>
    <Base:Details/>
    <Base:Combat>
      <Base:Strength value="1"/>
      <Base:MaxFatigue value="1"/>
    </Base:Combat>
    <Base:Clothing>
      <Base:SingleWear value="false"/>
    </Base:Clothing>
    <Base:Crafting see_level="0" do_level="0" time="0" attention="false" held="false">
      <Base:Ingredients/>
      <Base:Tools/>
      <Base:CraftVerbs/>
    </Base:Crafting>
    <Base:InitialContents/>
    <Base:InitialProperties/>
    <Core:Properties>
      <Core:Property property="chat:callback">([  ])</Core:Property>
      <Core:Property property="chat:cap">300</Core:Property>
      <Core:Property property="chat:command">"lfc"</Core:Property>
      <Core:Property property="chat:filters">
         ([ "commands":\<MOVED:20080918-114107:Lib:filter:lfc\>, "input":\<MOVED:20080918-114107:Lib:filter:lfc\>, "output":\<MOVED:20080918-114107:Lib:filter:lfc\> ])
      </Core:Property>
      <Core:Property property="chat:help">
         "LFC channel ('LogFeedChannel').\\n\\nThis is a LOG channel for scripts etc. \\n\\nType +lfc verbose [for a more thorough help]\\nType +lfc service [to list your hooks/ignore list]\\n\\nIt is easy to hook up your own script simply by setting a merry:inherit:lib:log to \<Lib:chatlib\>. (more info on TWiki)\\n\\nThe LFC channel is like a regular chat channel, except that it stores priority and ID tags in all messages. These tags can then be used to filter the messages you get when you keep LFC enabled, and also the messages you receive when doing a '+lfc recall'."
      </Core:Property>
      <Core:Property property="chat:history">
         (\{ "\<lfc pri=\\"7\\" id=\\"crond\\"\>00:00 [LFC] Crond: [Fri] Scheduled 11  executions [HD].", "\<lfc pri=\\"7\\" id=\\"crond\\"\>00:00 [LFC] Crond: [Sat] Scheduled 11  executions [HD].", "\<lfc pri=\\"7\\" id=\\"crond\\"\>00:00 [LFC] Crond: [Sun] Scheduled 14  executions [HDW].", "\<lfc pri=\\"7\\" id=\\"sharedcore\\"\>03:15 [LFC] SharedCore: Expanding shared folder; things might be laggy for a bit.", "\<lfc pri=\\"7\\" id=\\"crond\\"\>00:00 [LFC] Crond: [Mon] Scheduled 11  executions [HD].", "\<lfc pri=\\"7\\" id=\\"random1377\\"\>18:26 [LFC] Random1377: Sir Faust has been unfrozen.", "\<lfc pri=\\"7\\" id=\\"crond\\"\>00:00 [LFC] Crond: [Tue] Scheduled 11  executions [HD].", "\<lfc pri=\\"7\\" id=\\"crond\\"\>00:00 [LFC] Crond: [Wed] Scheduled 11  executions [HD].", "\<lfc pri=\\"7\\" id=\\"crond\\"\>00:00 [LFC] Crond: [Thu] Scheduled 11  executions [HD].", "\<lfc pri=\\"7\\" id=\\"crond\\"\>00:00 [LFC] Crond: [Fri] Scheduled 11  executions [HD].", "\<lfc pri=\\"7\\" id=\\"ezralee\\"\>14:28 [LFC] Ezralee: Lady Emmaline has been unfrozen.", "\<lfc pri=\\"7\\" id=\\"annemairi\\"\>17:20 [LFC] Annemairi: Duke Archibald has been unfrozen.", "\<lfc pri=\\"7\\" id=\\"crond\\"\>00:00 [LFC] Crond: [Sat] Scheduled 11  executions [HD].", "\<lfc pri=\\"7\\" id=\\"crond\\"\>00:00 [LFC] Crond: [Sun] Scheduled 14  executions [HDW].", "\<lfc pri=\\"7\\" id=\\"sharedcore\\"\>03:15 [LFC] SharedCore: Expanding shared folder; things might be laggy for a bit.", "\<lfc pri=\\"7\\" id=\\"crond\\"\>00:00 [LFC] Crond: [Mon] Scheduled 11  executions [HD].", "\<lfc pri=\\"7\\" id=\\"crond\\"\>00:00 [LFC] Crond: [Tue] Scheduled 11  executions [HD].", "\<lfc pri=\\"7\\" id=\\"crond\\"\>00:00 [LFC] Crond: [Wed] Scheduled 11  executions [HD].", "\<lfc pri=\\"7\\" id=\\"crond\\"\>00:00 [LFC] Crond: [Thu] Scheduled 11  executions [HD].", "\<lfc pri=\\"7\\" id=\\"crond\\"\>00:00 [LFC] Crond: [Fri] Scheduled 11  executions [HD].", "\<lfc pri=\\"7\\" id=\\"annemairi\\"\>17:02 [LFC] Annemairi: Queen Emeraude has been unfrozen.", "\<lfc pri=\\"7\\" id=\\"mg\\"\>18:28 [LFC] MG: Too many active PCs. Freezing them all so the right ones can be unfrozen.", "\<lfc pri=\\"7\\" id=\\"mg\\"\>18:28 [LFC] MG: Max should be 1. Currently is: ([ \\"active\\":(\{ \<Chatters:AE:va:valentin\>, \<Chatters:AE:sa:salvatore\>, \<Chatters:AE:br:brok\>, \<Chatters:AE:gi:giacomo\>, \<Chatters:AE:fu:fuego\> \}), \\"mothballed\\":(\{  \}), \\"nocost\\":(\{  \}) ])", "\<lfc pri=\\"7\\" id=\\"rgendron02\\"\>18:28 [LFC] Rgendron02: Salvatore has been unfrozen.", "\<lfc pri=\\"7\\" id=\\"rgendron02\\"\>18:30 [LFC] Rgendron02: Valentin has been unfrozen.", "\<lfc pri=\\"7\\" id=\\"rgendron02\\"\>18:31 [LFC] Rgendron02: Lord Giacomo has been unfrozen.", "\<lfc pri=\\"7\\" id=\\"rgendron02\\"\>18:32 [LFC] Rgendron02: Fuego has been unfrozen.", "\<lfc pri=\\"7\\" id=\\"crond\\"\>00:00 [LFC] Crond: [Sat] Scheduled 11  executions [HD].", "\<lfc pri=\\"7\\" id=\\"annemairi\\"\>17:15 [LFC] Annemairi: Captain Selene has been unfrozen.", "\<lfc pri=\\"7\\" id=\\"crond\\"\>00:00 [LFC] Crond: [Sun] Scheduled 14  executions [HDW].", "\<lfc pri=\\"7\\" id=\\"sharedcore\\"\>03:15 [LFC] SharedCore: Expanding shared folder; things might be laggy for a bit.", "\<lfc pri=\\"7\\" id=\\"rgendron02\\"\>09:05 [LFC] Rgendron02: Brok has been unfrozen.", "\<lfc pri=\\"7\\" id=\\"crond\\"\>00:00 [LFC] Crond: [Mon] Scheduled 11  executions [HD].", "\<lfc pri=\\"7\\" id=\\"crond\\"\>00:00 [LFC] Crond: [Tue] Scheduled 11  executions [HD].", "\<lfc pri=\\"7\\" id=\\"crond\\"\>00:00 [LFC] Crond: [Wed] Scheduled 11  executions [HD].", "\<lfc pri=\\"7\\" id=\\"crond\\"\>00:00 [LFC] Crond: [Thu] Scheduled 11  executions [HD].", "\<lfc pri=\\"7\\" id=\\"crond\\"\>00:00 [LFC] Crond: [Fri] Scheduled 11  executions [HD].", "\<lfc pri=\\"7\\" id=\\"sandon\\"\>09:18 [LFC] Sandon: Jadrius has been unfrozen.", "\<lfc pri=\\"7\\" id=\\"crond\\"\>00:00 [LFC] Crond: [Sat] Scheduled 11  executions [HD].", "\<lfc pri=\\"7\\" id=\\"crond\\"\>00:00 [LFC] Crond: [Sun] Scheduled 14  executions [HDW].", "\<lfc pri=\\"7\\" id=\\"sharedcore\\"\>03:15 [LFC] SharedCore: Expanding shared folder; things might be laggy for a bit.", "\<lfc pri=\\"7\\" id=\\"ezralee\\"\>19:05 [LFC] Ezralee: Elle has been unfrozen.", "\<lfc pri=\\"7\\" id=\\"crond\\"\>00:00 [LFC] Crond: [Mon] Scheduled 12  executions [HDM].", "\<lfc pri=\\"7\\" id=\\"ezralee\\"\>16:13 [LFC] Ezralee: StoryHostess Topsy has been unfrozen.", "\<lfc pri=\\"7\\" id=\\"ezralee\\"\>16:13 [LFC] Ezralee: Eliseo has been unfrozen.", "\<lfc pri=\\"7\\" id=\\"crond\\"\>00:00 [LFC] Crond: [Tue] Scheduled 11  executions [HD].", "\<lfc pri=\\"7\\" id=\\"crond\\"\>00:00 [LFC] Crond: [Wed] Scheduled 11  executions [HD].", "\<lfc pri=\\"7\\" id=\\"crond\\"\>00:00 [LFC] Crond: [Thu] Scheduled 11  executions [HD].", "\<lfc pri=\\"7\\" id=\\"annemairi\\"\>02:06 [LFC] Annemairi: Abbess Simonetta has been unfrozen.", "\<lfc pri=\\"7\\" id=\\"crond\\"\>00:00 [LFC] Crond: [Fri] Scheduled 11  executions [HD].", "\<lfc pri=\\"7\\" id=\\"crond\\"\>00:00 [LFC] Crond: [Sat] Scheduled 11  executions [HD].", "\<lfc pri=\\"7\\" id=\\"crond\\"\>00:00 [LFC] Crond: [Sun] Scheduled 14  executions [HDW].", "\<lfc pri=\\"7\\" id=\\"sharedcore\\"\>03:15 [LFC] SharedCore: Expanding shared folder; things might be laggy for a bit.", "\<lfc pri=\\"7\\" id=\\"crond\\"\>00:00 [LFC] Crond: [Mon] Scheduled 11  executions [HD].", "\<lfc pri=\\"7\\" id=\\"ezralee\\"\>20:21 [LFC] Ezralee: Giovanni has been unfrozen.", "\<lfc pri=\\"7\\" id=\\"ezralee\\"\>20:33 [LFC] Ezralee: General Dario has been unfrozen.", "\<lfc pri=\\"7\\" id=\\"crond\\"\>00:00 [LFC] Crond: [Tue] Scheduled 11  executions [HD].", "\<lfc pri=\\"7\\" id=\\"linda123\\"\>12:10 [LFC] Linda123: Ella has been unfrozen.", "\<lfc pri=\\"7\\" id=\\"annemairi\\"\>19:08 [LFC] Annemairi: Archbishop Benizio has been unfrozen.", "\<lfc pri=\\"7\\" id=\\"crond\\"\>00:00 [LFC] Crond: [Wed] Scheduled 11  executions [HD].", "\<lfc pri=\\"7\\" id=\\"crond\\"\>00:00 [LFC] Crond: [Thu] Scheduled 11  executions [HD].", "\<lfc pri=\\"7\\" id=\\"crond\\"\>00:00 [LFC] Crond: [Fri] Scheduled 11  executions [HD].", "\<lfc pri=\\"7\\" id=\\"maegovannen\\"\>19:04 [LFC] Maegovannen: Countess Serafina has been unfrozen.", "\<lfc pri=\\"7\\" id=\\"crond\\"\>00:00 [LFC] Crond: [Sat] Scheduled 11  executions [HD].", "\<lfc pri=\\"7\\" id=\\"crond\\"\>00:00 [LFC] Crond: [Sun] Scheduled 14  executions [HDW].", "\<lfc pri=\\"7\\" id=\\"sharedcore\\"\>03:15 [LFC] SharedCore: Expanding shared folder; things might be laggy for a bit.", "\<lfc pri=\\"7\\" id=\\"elaquin\\"\>20:39 [LFC] Elaquin: Alexandre has been unfrozen.", "\<lfc pri=\\"7\\" id=\\"crond\\"\>00:00 [LFC] Crond: [Mon] Scheduled 11  executions [HD].", "\<lfc pri=\\"7\\" id=\\"crond\\"\>00:00 [LFC] Crond: [Tue] Scheduled 11  executions [HD].", "\<lfc pri=\\"7\\" id=\\"crond\\"\>00:00 [LFC] Crond: [Wed] Scheduled 11  executions [HD].", "\<lfc pri=\\"7\\" id=\\"crond\\"\>00:00 [LFC] Crond: [Thu] Scheduled 11  executions [HD].", "\<lfc pri=\\"7\\" id=\\"crond\\"\>00:00 [LFC] Crond: [Fri] Scheduled 11  executions [HD].", "\<lfc pri=\\"7\\" id=\\"crond\\"\>00:00 [LFC] Crond: [Sat] Scheduled 11  executions [HD].", "\<lfc pri=\\"7\\" id=\\"crond\\"\>00:00 [LFC] Crond: [Sun] Scheduled 14  executions [HDW].", "\<lfc pri=\\"7\\" id=\\"sharedcore\\"\>03:15 [LFC] SharedCore: Expanding shared folder; things might be laggy for a bit.", "\<lfc pri=\\"7\\" id=\\"mg\\"\>11:20 [LFC] MG: Too many active PCs. Freezing them all so the right ones can be unfrozen.", "\<lfc pri=\\"7\\" id=\\"mg\\"\>11:20 [LFC] MG: Max should be 1. Currently is: ([ \\"active\\":(\{ \<Chatters:AE:va:valentin\>, \<Chatters:AE:sa:salvatore\>, \<Chatters:AE:br:brok\>, \<Chatters:AE:gi:giacomo\>, \<Chatters:AE:fu:fuego\> \}), \\"mothballed\\":(\{  \}), \\"nocost\\":(\{  \}) ])", "\<lfc pri=\\"7\\" id=\\"rgendron02\\"\>11:20 [LFC] Rgendron02: Salvatore has been unfrozen.", "\<lfc pri=\\"7\\" id=\\"rgendron02\\"\>11:21 [LFC] Rgendron02: Valentin has been unfrozen.", "\<lfc pri=\\"7\\" id=\\"rgendron02\\"\>11:22 [LFC] Rgendron02: Lord Giacomo has been unfrozen.", "\<lfc pri=\\"7\\" id=\\"rgendron02\\"\>11:22 [LFC] Rgendron02: Fuego has been unfrozen.", "\<lfc pri=\\"7\\" id=\\"crond\\"\>00:00 [LFC] Crond: [Mon] Scheduled 11  executions [HD].", "\<lfc pri=\\"7\\" id=\\"asernova\\"\>18:27 [LFC] Asernova: Tomaso has been unfrozen.", "\<lfc pri=\\"7\\" id=\\"crond\\"\>00:00 [LFC] Crond: [Tue] Scheduled 11  executions [HD].", "\<lfc pri=\\"7\\" id=\\"crond\\"\>00:00 [LFC] Crond: [Wed] Scheduled 11  executions [HD].", "\<lfc pri=\\"7\\" id=\\"crond\\"\>00:00 [LFC] Crond: [Thu] Scheduled 11  executions [HD].", "\<lfc pri=\\"7\\" id=\\"crond\\"\>00:00 [LFC] Crond: [Fri] Scheduled 11  executions [HD].", "\<lfc pri=\\"7\\" id=\\"crond\\"\>00:00 [LFC] Crond: [Sat] Scheduled 11  executions [HD].", "\<lfc pri=\\"7\\" id=\\"crond\\"\>00:00 [LFC] Crond: [Sun] Scheduled 14  executions [HDW].", "\<lfc pri=\\"7\\" id=\\"sharedcore\\"\>03:15 [LFC] SharedCore: Expanding shared folder; things might be laggy for a bit.", "\<lfc pri=\\"7\\" id=\\"ncs\\"\>13:56 [LFC] NCS: Global update; 0 affected nippers. ETA 0d 0h 00m 00s.", "\<lfc pri=\\"7\\" id=\\"ezralee\\"\>19:45 [LFC] Ezralee: Prince Calixto has been unfrozen.", "\<lfc pri=\\"7\\" id=\\"ezralee\\"\>19:46 [LFC] Ezralee: Queen Liza has been unfrozen.", "\<lfc pri=\\"7\\" id=\\"ezralee\\"\>19:48 [LFC] Ezralee: Captain Owen has been unfrozen.", "\<lfc pri=\\"7\\" id=\\"mezerbo\\"\>22:16 [LFC] Mezerbo: Poe has been unfrozen.", "\<lfc pri=\\"7\\" id=\\"skiwaymtn\\"\>23:04 [LFC] Skiwaymtn: Mother Eidain has been unfrozen.", "\<lfc pri=\\"7\\" id=\\"crond\\"\>00:00 [LFC] Crond: [Mon] Scheduled 11  executions [HD].", "\<lfc pri=\\"7\\" id=\\"crond\\"\>00:00 [LFC] Crond: [Tue] Scheduled 11  executions [HD].", "\<lfc pri=\\"7\\" id=\\"crond\\"\>00:00 [LFC] Crond: [Wed] Scheduled 11  executions [HD].", "\<lfc pri=\\"7\\" id=\\"crond\\"\>00:00 [LFC] Crond: [Thu] Scheduled 12  executions [HDM].", "\<lfc pri=\\"7\\" id=\\"crond\\"\>00:00 [LFC] Crond: [Fri] Scheduled 11  executions [HD].", "\<lfc pri=\\"7\\" id=\\"crond\\"\>00:00 [LFC] Crond: [Sat] Scheduled 11  executions [HD].", "\<lfc pri=\\"7\\" id=\\"crond\\"\>00:00 [LFC] Crond: [Sun] Scheduled 14  executions [HDW].", "\<lfc pri=\\"7\\" id=\\"sharedcore\\"\>03:15 [LFC] SharedCore: Expanding shared folder; things might be laggy for a bit.", "\<lfc pri=\\"7\\" id=\\"crond\\"\>00:00 [LFC] Crond: [Mon] Scheduled 11  executions [HD].", "\<lfc pri=\\"7\\" id=\\"crond\\"\>00:00 [LFC] Crond: [Tue] Scheduled 11  executions [HD].", "\<lfc pri=\\"7\\" id=\\"crond\\"\>00:00 [LFC] Crond: [Wed] Scheduled 11  executions [HD].", "\<lfc pri=\\"7\\" id=\\"crond\\"\>00:00 [LFC] Crond: [Thu] Scheduled 11  executions [HD].", "\<lfc pri=\\"7\\" id=\\"crond\\"\>00:00 [LFC] Crond: [Fri] Scheduled 11  executions [HD].", "\<lfc pri=\\"7\\" id=\\"crond\\"\>00:00 [LFC] Crond: [Sat] Scheduled 11  executions [HD].", "\<lfc pri=\\"7\\" id=\\"crond\\"\>00:00 [LFC] Crond: [Sun] Scheduled 14  executions [HDW].", "\<lfc pri=\\"7\\" id=\\"sharedcore\\"\>03:15 [LFC] SharedCore: Expanding shared folder; things might be laggy for a bit.", "\<lfc pri=\\"7\\" id=\\"crond\\"\>00:00 [LFC] Crond: [Mon] Scheduled 11  executions [HD].", "\<lfc pri=\\"7\\" id=\\"crond\\"\>00:00 [LFC] Crond: [Tue] Scheduled 11  executions [HD].", "\<lfc pri=\\"7\\" id=\\"crond\\"\>00:00 [LFC] Crond: [Wed] Scheduled 11  executions [HD].", "\<lfc pri=\\"7\\" id=\\"crond\\"\>00:00 [LFC] Crond: [Thu] Scheduled 11  executions [HD].", "\<lfc pri=\\"7\\" id=\\"crond\\"\>00:00 [LFC] Crond: [Fri] Scheduled 11  executions [HD].", "\<lfc pri=\\"7\\" id=\\"crond\\"\>00:00 [LFC] Crond: [Sat] Scheduled 11  executions [HD].", "\<lfc pri=\\"7\\" id=\\"crond\\"\>00:00 [LFC] Crond: [Sun] Scheduled 14  executions [HDW].", "\<lfc pri=\\"7\\" id=\\"sharedcore\\"\>03:15 [LFC] SharedCore: Expanding shared folder; things might be laggy for a bit.", "\<lfc pri=\\"7\\" id=\\"crond\\"\>00:00 [LFC] Crond: [Mon] Scheduled 11  executions [HD].", "\<lfc pri=\\"7\\" id=\\"crond\\"\>00:00 [LFC] Crond: [Tue] Scheduled 11  executions [HD].", "\<lfc pri=\\"7\\" id=\\"crond\\"\>00:00 [LFC] Crond: [Wed] Scheduled 11  executions [HD].", "\<lfc pri=\\"7\\" id=\\"crond\\"\>00:00 [LFC] Crond: [Thu] Scheduled 11  executions [HD].", "\<lfc pri=\\"7\\" id=\\"crond\\"\>00:00 [LFC] Crond: [Fri] Scheduled 11  executions [HD].", "\<lfc pri=\\"7\\" id=\\"crond\\"\>00:00 [LFC] Crond: [Sat] Scheduled 11  executions [HD].", "\<lfc pri=\\"7\\" id=\\"mg\\"\>07:53 [LFC] MG: Too many active PCs. Freezing them all so the right ones can be unfrozen.", "\<lfc pri=\\"7\\" id=\\"mg\\"\>07:53 [LFC] MG: Max should be 1. Currently is: ([ \\"active\\":(\{ \<Chatters:AE:va:valentin\>, \<Chatters:AE:sa:salvatore\>, \<Chatters:AE:gi:giacomo\>, \<Chatters:AE:fu:fuego\> \}), \\"mothballed\\":(\{ \<Chatters:AE:br:brok\> \}), \\"nocost\\":(\{  \}) ])", "\<lfc pri=\\"7\\" id=\\"rgendron02\\"\>07:54 [LFC] Rgendron02: Valentin has been unfrozen.", "\<lfc pri=\\"7\\" id=\\"rgendron02\\"\>07:54 [LFC] Rgendron02: Lord Giacomo is frozen, and has been disconnected.", "\<lfc pri=\\"7\\" id=\\"rgendron02\\"\>07:54 [LFC] Rgendron02: Lord Giacomo is frozen, and has been disconnected.", "\<lfc pri=\\"7\\" id=\\"rgendron02\\"\>07:54 [LFC] Rgendron02: Lord Giacomo is frozen, and has been disconnected.", "\<lfc pri=\\"7\\" id=\\"rgendron02\\"\>07:54 [LFC] Rgendron02: Lord Giacomo is frozen, and has been disconnected.", "\<lfc pri=\\"7\\" id=\\"rgendron02\\"\>07:54 [LFC] Rgendron02: Salvatore is frozen, and has been disconnected.", "\<lfc pri=\\"7\\" id=\\"rgendron02\\"\>07:54 [LFC] Rgendron02: Salvatore is frozen, and has been disconnected.", "\<lfc pri=\\"7\\" id=\\"rgendron02\\"\>07:54 [LFC] Rgendron02: Salvatore is frozen, and has been disconnected.", "\<lfc pri=\\"7\\" id=\\"rgendron02\\"\>07:54 [LFC] Rgendron02: Salvatore is frozen, and has been disconnected.", "\<lfc pri=\\"7\\" id=\\"crond\\"\>00:00 [LFC] Crond: [Sun] Scheduled 14  executions [HDW].", "\<lfc pri=\\"7\\" id=\\"sharedcore\\"\>03:15 [LFC] SharedCore: Expanding shared folder; things might be laggy for a bit.", "\<lfc pri=\\"7\\" id=\\"crond\\"\>00:00 [LFC] Crond: [Mon] Scheduled 11  executions [HD].", "\<lfc pri=\\"7\\" id=\\"annemairi\\"\>10:53 [LFC] Annemairi: Persephone has been unfrozen.", "\<lfc pri=\\"7\\" id=\\"crond\\"\>00:00 [LFC] Crond: [Tue] Scheduled 11  executions [HD].", "\<lfc pri=\\"7\\" id=\\"crond\\"\>00:00 [LFC] Crond: [Wed] Scheduled 11  executions [HD].", "\<lfc pri=\\"7\\" id=\\"mg\\"\>19:44 [LFC] MG: Too many active PCs. Freezing them all so the right ones can be unfrozen.", "\<lfc pri=\\"7\\" id=\\"mg\\"\>19:44 [LFC] MG: Max should be 1. Currently is: ([ \\"active\\":(\{ \<Chatters:AE:ki:kilana\>, \<Chatters:AE:ei:eidain\> \}), \\"mothballed\\":(\{ \<Chatters:AE:me:merveille\>, \<Chatters:AE:fl:flora\> \}), \\"nocost\\":(\{  \}) ])", "\<lfc pri=\\"7\\" id=\\"skiwaymtn\\"\>19:44 [LFC] Skiwaymtn: Kilana has been unfrozen.", "\<lfc pri=\\"7\\" id=\\"crond\\"\>00:00 [LFC] Crond: [Thu] Scheduled 11  executions [HD].", "\<lfc pri=\\"7\\" id=\\"madalina\\"\>01:03 [LFC] Madalina: Esmerelda has been unfrozen.", "\<lfc pri=\\"7\\" id=\\"crond\\"\>00:00 [LFC] Crond: [Fri] Scheduled 11  executions [HD].", "\<lfc pri=\\"7\\" id=\\"crond\\"\>00:00 [LFC] Crond: [Sat] Scheduled 11  executions [HD].", "\<lfc pri=\\"7\\" id=\\"crond\\"\>00:00 [LFC] Crond: [Sun] Scheduled 15  executions [HDWM].", "\<lfc pri=\\"7\\" id=\\"sharedcore\\"\>03:15 [LFC] SharedCore: Expanding shared folder; things might be laggy for a bit.", "\<lfc pri=\\"7\\" id=\\"crond\\"\>00:00 [LFC] Crond: [Mon] Scheduled 11  executions [HD].", "\<lfc pri=\\"7\\" id=\\"crond\\"\>00:00 [LFC] Crond: [Tue] Scheduled 11  executions [HD].", "\<lfc pri=\\"7\\" id=\\"crond\\"\>00:00 [LFC] Crond: [Wed] Scheduled 11  executions [HD].", "\<lfc pri=\\"7\\" id=\\"crond\\"\>00:00 [LFC] Crond: [Thu] Scheduled 11  executions [HD].", "\<lfc pri=\\"7\\" id=\\"crond\\"\>00:00 [LFC] Crond: [Fri] Scheduled 11  executions [HD].", "\<lfc pri=\\"7\\" id=\\"crond\\"\>00:00 [LFC] Crond: [Sat] Scheduled 11  executions [HD].", "\<lfc pri=\\"7\\" id=\\"crond\\"\>00:00 [LFC] Crond: [Sun] Scheduled 14  executions [HDW].", "\<lfc pri=\\"7\\" id=\\"sharedcore\\"\>03:15 [LFC] SharedCore: Expanding shared folder; things might be laggy for a bit.", "\<lfc pri=\\"7\\" id=\\"crond\\"\>00:00 [LFC] Crond: [Mon] Scheduled 11  executions [HD].", "\<lfc pri=\\"7\\" id=\\"crond\\"\>00:00 [LFC] Crond: [Tue] Scheduled 11  executions [HD].", "\<lfc pri=\\"7\\" id=\\"crond\\"\>00:00 [LFC] Crond: [Wed] Scheduled 11  executions [HD].", "\<lfc pri=\\"7\\" id=\\"crond\\"\>00:00 [LFC] Crond: [Thu] Scheduled 11  executions [HD].", "\<lfc pri=\\"7\\" id=\\"crond\\"\>00:00 [LFC] Crond: [Fri] Scheduled 11  executions [HD].", "\<lfc pri=\\"7\\" id=\\"crond\\"\>00:00 [LFC] Crond: [Sat] Scheduled 11  executions [HD].", "\<lfc pri=\\"7\\" id=\\"crond\\"\>00:00 [LFC] Crond: [Sun] Scheduled 14  executions [HDW].", "\<lfc pri=\\"7\\" id=\\"sharedcore\\"\>03:15 [LFC] SharedCore: Expanding shared folder; things might be laggy for a bit.", "\<lfc pri=\\"7\\" id=\\"crond\\"\>00:00 [LFC] Crond: [Mon] Scheduled 11  executions [HD].", "\<lfc pri=\\"7\\" id=\\"crond\\"\>00:00 [LFC] Crond: [Tue] Scheduled 11  executions [HD].", "\<lfc pri=\\"7\\" id=\\"crond\\"\>00:00 [LFC] Crond: [Wed] Scheduled 11  executions [HD].", "\<lfc pri=\\"7\\" id=\\"crond\\"\>00:00 [LFC] Crond: [Thu] Scheduled 11  executions [HD].", "\<lfc pri=\\"7\\" id=\\"jominey\\"\>21:36 [LFC] Jominey: Bruno has been unfrozen.", "\<lfc pri=\\"7\\" id=\\"crond\\"\>00:00 [LFC] Crond: [Fri] Scheduled 11  executions [HD].", "\<lfc pri=\\"7\\" id=\\"crond\\"\>00:00 [LFC] Crond: [Sat] Scheduled 11  executions [HD].", "\<lfc pri=\\"7\\" id=\\"crond\\"\>00:00 [LFC] Crond: [Sun] Scheduled 14  executions [HDW].", "\<lfc pri=\\"7\\" id=\\"sharedcore\\"\>03:15 [LFC] SharedCore: Expanding shared folder; things might be laggy for a bit.", "\<lfc pri=\\"7\\" id=\\"crond\\"\>00:00 [LFC] Crond: [Mon] Scheduled 11  executions [HD].", "\<lfc pri=\\"7\\" id=\\"crond\\"\>00:00 [LFC] Crond: [Tue] Scheduled 11  executions [HD].", "\<lfc pri=\\"7\\" id=\\"crond\\"\>00:00 [LFC] Crond: [Wed] Scheduled 11  executions [HD].", "\<lfc pri=\\"7\\" id=\\"crond\\"\>00:00 [LFC] Crond: [Thu] Scheduled 11  executions [HD].", "\<lfc pri=\\"7\\" id=\\"crond\\"\>00:00 [LFC] Crond: [Fri] Scheduled 11  executions [HD].", "\<lfc pri=\\"7\\" id=\\"crond\\"\>00:00 [LFC] Crond: [Sat] Scheduled 11  executions [HD].", "\<lfc pri=\\"7\\" id=\\"crond\\"\>00:00 [LFC] Crond: [Sun] Scheduled 14  executions [HDW].", "\<lfc pri=\\"7\\" id=\\"sharedcore\\"\>03:15 [LFC] SharedCore: Expanding shared folder; things might be laggy for a bit.", "\<lfc pri=\\"7\\" id=\\"crond\\"\>00:00 [LFC] Crond: [Mon] Scheduled 11  executions [HD].", "\<lfc pri=\\"7\\" id=\\"crond\\"\>00:00 [LFC] Crond: [Tue] Scheduled 12  executions [HDM].", "\<lfc pri=\\"7\\" id=\\"crond\\"\>00:00 [LFC] Crond: [Wed] Scheduled 11  executions [HD].", "\<lfc pri=\\"7\\" id=\\"crond\\"\>00:00 [LFC] Crond: [Thu] Scheduled 11  executions [HD].", "\<lfc pri=\\"7\\" id=\\"crond\\"\>00:00 [LFC] Crond: [Fri] Scheduled 11  executions [HD].", "\<lfc pri=\\"7\\" id=\\"crond\\"\>00:00 [LFC] Crond: [Sat] Scheduled 11  executions [HD].", "\<lfc pri=\\"7\\" id=\\"crond\\"\>00:00 [LFC] Crond: [Sun] Scheduled 14  executions [HDW].", "\<lfc pri=\\"7\\" id=\\"sharedcore\\"\>03:15 [LFC] SharedCore: Expanding shared folder; things might be laggy for a bit.", "\<lfc pri=\\"7\\" id=\\"crond\\"\>00:00 [LFC] Crond: [Mon] Scheduled 11  executions [HD].", "\<lfc pri=\\"7\\" id=\\"crond\\"\>00:00 [LFC] Crond: [Tue] Scheduled 11  executions [HD].", "\<lfc pri=\\"7\\" id=\\"crond\\"\>00:00 [LFC] Crond: [Wed] Scheduled 11  executions [HD].", "\<lfc pri=\\"7\\" id=\\"crond\\"\>00:00 [LFC] Crond: [Thu] Scheduled 11  executions [HD].", "\<lfc pri=\\"7\\" id=\\"crond\\"\>00:00 [LFC] Crond: [Fri] Scheduled 11  executions [HD].", "\<lfc pri=\\"7\\" id=\\"crond\\"\>00:00 [LFC] Crond: [Sat] Scheduled 11  executions [HD].", "\<lfc pri=\\"7\\" id=\\"crond\\"\>00:00 [LFC] Crond: [Sun] Scheduled 14  executions [HDW].", "\<lfc pri=\\"7\\" id=\\"sharedcore\\"\>03:15 [LFC] SharedCore: Expanding shared folder; things might be laggy for a bit.", "\<lfc pri=\\"7\\" id=\\"crond\\"\>00:00 [LFC] Crond: [Mon] Scheduled 11  executions [HD].", "\<lfc pri=\\"7\\" id=\\"crond\\"\>00:00 [LFC] Crond: [Tue] Scheduled 11  executions [HD].", "\<lfc pri=\\"7\\" id=\\"crond\\"\>00:00 [LFC] Crond: [Wed] Scheduled 11  executions [HD].", "\<lfc pri=\\"7\\" id=\\"delfina\\"\>01:50 [LFC] Delfina: Sister Eloise has been unfrozen.", "\<lfc pri=\\"7\\" id=\\"crond\\"\>00:00 [LFC] Crond: [Thu] Scheduled 11  executions [HD].", "\<lfc pri=\\"7\\" id=\\"crond\\"\>00:00 [LFC] Crond: [Fri] Scheduled 11  executions [HD].", "\<lfc pri=\\"7\\" id=\\"crond\\"\>00:00 [LFC] Crond: [Sat] Scheduled 11  executions [HD].", "\<lfc pri=\\"7\\" id=\\"crond\\"\>00:00 [LFC] Crond: [Sun] Scheduled 14  executions [HDW].", "\<lfc pri=\\"7\\" id=\\"sharedcore\\"\>03:15 [LFC] SharedCore: Expanding shared folder; things might be laggy for a bit.", "\<lfc pri=\\"7\\" id=\\"crond\\"\>00:00 [LFC] Crond: [Mon] Scheduled 11  executions [HD].", "\<lfc pri=\\"7\\" id=\\"random1377\\"\>23:49 [LFC] Random1377: Sir Faust has been unfrozen.", "\<lfc pri=\\"7\\" id=\\"crond\\"\>00:00 [LFC] Crond: [Tue] Scheduled 11  executions [HD].", "\<lfc pri=\\"7\\" id=\\"annemairi\\"\>10:46 [LFC] Annemairi: Queen Emeraude has been unfrozen.", "\<lfc pri=\\"7\\" id=\\"annemairi\\"\>12:16 [LFC] Annemairi: Captain Selene has been unfrozen.", "\<lfc pri=\\"7\\" id=\\"crond\\"\>00:00 [LFC] Crond: [Wed] Scheduled 11  executions [HD].", "\<lfc pri=\\"7\\" id=\\"crond\\"\>00:00 [LFC] Crond: [Thu] Scheduled 11  executions [HD].", "\<lfc pri=\\"7\\" id=\\"crond\\"\>00:00 [LFC] Crond: [Fri] Scheduled 11  executions [HD].", "\<lfc pri=\\"7\\" id=\\"maegovannen\\"\>18:52 [LFC] Maegovannen: Countess Serafina has been unfrozen.", "\<lfc pri=\\"7\\" id=\\"maegovannen\\"\>19:00 [LFC] Maegovannen: Dame Katrina is frozen, and has been disconnected.", "\<lfc pri=\\"7\\" id=\\"crond\\"\>00:00 [LFC] Crond: [Sat] Scheduled 11  executions [HD].", "\<lfc pri=\\"7\\" id=\\"crond\\"\>00:00 [LFC] Crond: [Sun] Scheduled 14  executions [HDW].", "\<lfc pri=\\"7\\" id=\\"sharedcore\\"\>03:15 [LFC] SharedCore: Expanding shared folder; things might be laggy for a bit.", "\<lfc pri=\\"7\\" id=\\"crond\\"\>00:00 [LFC] Crond: [Mon] Scheduled 11  executions [HD].", "\<lfc pri=\\"7\\" id=\\"crond\\"\>00:00 [LFC] Crond: [Tue] Scheduled 11  executions [HD].", "\<lfc pri=\\"7\\" id=\\"crond\\"\>00:00 [LFC] Crond: [Wed] Scheduled 11  executions [HD].", "\<lfc pri=\\"7\\" id=\\"elaquin\\"\>10:46 [LFC] Elaquin: Alexandre has been unfrozen.", "\<lfc pri=\\"7\\" id=\\"crond\\"\>00:00 [LFC] Crond: [Thu] Scheduled 11  executions [HD].", "\<lfc pri=\\"7\\" id=\\"crond\\"\>00:00 [LFC] Crond: [Fri] Scheduled 12  executions [HDM].", "\<lfc pri=\\"7\\" id=\\"crond\\"\>00:00 [LFC] Crond: [Sat] Scheduled 11  executions [HD].", "\<lfc pri=\\"7\\" id=\\"crond\\"\>00:00 [LFC] Crond: [Sun] Scheduled 14  executions [HDW].", "\<lfc pri=\\"7\\" id=\\"sharedcore\\"\>02:15 [LFC] SharedCore: Expanding shared folder; things might be laggy for a bit.", "\<lfc pri=\\"7\\" id=\\"crond\\"\>00:00 [LFC] Crond: [Mon] Scheduled 11  executions [HD].", "\<lfc pri=\\"7\\" id=\\"crond\\"\>00:00 [LFC] Crond: [Tue] Scheduled 11  executions [HD].", "\<lfc pri=\\"7\\" id=\\"crond\\"\>00:00 [LFC] Crond: [Wed] Scheduled 11  executions [HD].", "\<lfc pri=\\"7\\" id=\\"crond\\"\>00:00 [LFC] Crond: [Thu] Scheduled 11  executions [HD].", "\<lfc pri=\\"7\\" id=\\"crond\\"\>00:00 [LFC] Crond: [Fri] Scheduled 11  executions [HD].", "\<lfc pri=\\"7\\" id=\\"ezralee\\"\>10:52 [LFC] Ezralee: StoryHostess Topsy has been unfrozen.", "\<lfc pri=\\"7\\" id=\\"ezralee\\"\>12:29 [LFC] Ezralee: Lady-in-Waiting Elle has been unfrozen.", "\<lfc pri=\\"7\\" id=\\"annemairi\\"\>19:05 [LFC] Annemairi: StoryMediator Melinoe has been unfrozen.", "\<lfc pri=\\"7\\" id=\\"crond\\"\>00:00 [LFC] Crond: [Sat] Scheduled 11  executions [HD].", "\<lfc pri=\\"7\\" id=\\"rgendron02\\"\>07:44 [LFC] Rgendron02: Salvatore has been unfrozen.", "\<lfc pri=\\"7\\" id=\\"rgendron02\\"\>07:45 [LFC] Rgendron02: Brok has been unfrozen.", "\<lfc pri=\\"7\\" id=\\"rgendron02\\"\>07:46 [LFC] Rgendron02: Lord Giacomo has been unfrozen.", "\<lfc pri=\\"7\\" id=\\"rgendron02\\"\>07:47 [LFC] Rgendron02: Fuego has been unfrozen.", "\<lfc pri=\\"7\\" id=\\"crond\\"\>00:00 [LFC] Crond: [Sun] Scheduled 14  executions [HDW].", "\<lfc pri=\\"7\\" id=\\"sharedcore\\"\>03:15 [LFC] SharedCore: Expanding shared folder; things might be laggy for a bit.", "\<lfc pri=\\"7\\" id=\\"crond\\"\>00:00 [LFC] Crond: [Mon] Scheduled 11  executions [HD].", "\<lfc pri=\\"7\\" id=\\"crond\\"\>00:00 [LFC] Crond: [Tue] Scheduled 11  executions [HD].", "\<lfc pri=\\"7\\" id=\\"crond\\"\>00:00 [LFC] Crond: [Wed] Scheduled 11  executions [HD].", "\<lfc pri=\\"7\\" id=\\"crond\\"\>00:00 [LFC] Crond: [Thu] Scheduled 11  executions [HD].", "\<lfc pri=\\"7\\" id=\\"crond\\"\>00:00 [LFC] Crond: [Fri] Scheduled 11  executions [HD].", "\<lfc pri=\\"7\\" id=\\"crond\\"\>00:00 [LFC] Crond: [Sat] Scheduled 11  executions [HD].", "\<lfc pri=\\"7\\" id=\\"crond\\"\>00:00 [LFC] Crond: [Sun] Scheduled 14  executions [HDW].", "\<lfc pri=\\"7\\" id=\\"sharedcore\\"\>03:15 [LFC] SharedCore: Expanding shared folder; things might be laggy for a bit.", "\<lfc pri=\\"7\\" id=\\"crond\\"\>00:00 [LFC] Crond: [Mon] Scheduled 11  executions [HD].", "\<lfc pri=\\"7\\" id=\\"crond\\"\>00:00 [LFC] Crond: [Tue] Scheduled 11  executions [HD].", "\<lfc pri=\\"7\\" id=\\"crond\\"\>00:00 [LFC] Crond: [Wed] Scheduled 11  executions [HD].", "\<lfc pri=\\"7\\" id=\\"crond\\"\>00:00 [LFC] Crond: [Thu] Scheduled 11  executions [HD].", "\<lfc pri=\\"7\\" id=\\"crond\\"\>00:00 [LFC] Crond: [Fri] Scheduled 11  executions [HD].", "\<lfc pri=\\"7\\" id=\\"crond\\"\>00:00 [LFC] Crond: [Sat] Scheduled 11  executions [HD].", "\<lfc pri=\\"7\\" id=\\"crond\\"\>00:00 [LFC] Crond: [Sun] Scheduled 14  executions [HDW].", "\<lfc pri=\\"7\\" id=\\"sharedcore\\"\>03:15 [LFC] SharedCore: Expanding shared folder; things might be laggy for a bit.", "\<lfc pri=\\"7\\" id=\\"crond\\"\>00:00 [LFC] Crond: [Mon] Scheduled 11  executions [HD].", "\<lfc pri=\\"7\\" id=\\"crond\\"\>00:00 [LFC] Crond: [Tue] Scheduled 11  executions [HD].", "\<lfc pri=\\"7\\" id=\\"crond\\"\>00:00 [LFC] Crond: [Wed] Scheduled 11  executions [HD].", "\<lfc pri=\\"7\\" id=\\"crond\\"\>00:00 [LFC] Crond: [Thu] Scheduled 11  executions [HD].", "\<lfc pri=\\"7\\" id=\\"crond\\"\>00:00 [LFC] Crond: [Fri] Scheduled 11  executions [HD].", "\<lfc pri=\\"7\\" id=\\"crond\\"\>00:00 [LFC] Crond: [Sat] Scheduled 11  executions [HD].", "\<lfc pri=\\"7\\" id=\\"crond\\"\>00:00 [LFC] Crond: [Sun] Scheduled 15  executions [HDWM].", "\<lfc pri=\\"7\\" id=\\"sharedcore\\"\>03:15 [LFC] SharedCore: Expanding shared folder; things might be laggy for a bit.", "\<lfc pri=\\"7\\" id=\\"crond\\"\>00:00 [LFC] Crond: [Mon] Scheduled 11  executions [HD].", "\<lfc pri=\\"7\\" id=\\"crond\\"\>00:00 [LFC] Crond: [Tue] Scheduled 11  executions [HD].", "\<lfc pri=\\"7\\" id=\\"crond\\"\>00:00 [LFC] Crond: [Wed] Scheduled 11  executions [HD].", "\<lfc pri=\\"7\\" id=\\"crond\\"\>00:00 [LFC] Crond: [Thu] Scheduled 11  executions [HD].", "\<lfc pri=\\"7\\" id=\\"crond\\"\>00:00 [LFC] Crond: [Fri] Scheduled 11  executions [HD].", "\<lfc pri=\\"7\\" id=\\"crond\\"\>00:00 [LFC] Crond: [Sat] Scheduled 11  executions [HD].", "\<lfc pri=\\"7\\" id=\\"crond\\"\>00:00 [LFC] Crond: [Sun] Scheduled 14  executions [HDW].", "\<lfc pri=\\"7\\" id=\\"sharedcore\\"\>03:15 [LFC] SharedCore: Expanding shared folder; things might be laggy for a bit.", "\<lfc pri=\\"7\\" id=\\"crond\\"\>00:00 [LFC] Crond: [Mon] Scheduled 11  executions [HD].", "\<lfc pri=\\"7\\" id=\\"mg\\"\>15:41 [LFC] MG: Too many active PCs. Freezing them all so the right ones can be unfrozen.", "\<lfc pri=\\"7\\" id=\\"mg\\"\>15:41 [LFC] MG: Max should be 1. Currently is: ([ \\"active\\":(\{ \<Chatters:AE:va:valentin\>, \<Chatters:AE:sa:salvatore\>, \<Chatters:AE:br:brok\>, \<Chatters:AE:gi:giacomo\>, \<Chatters:AE:fu:fuego\> \}), \\"mothballed\\":(\{  \}), \\"nocost\\":(\{  \}) ])", "\<lfc pri=\\"7\\" id=\\"rgendron02\\"\>15:41 [LFC] Rgendron02: Salvatore has been unfrozen.", "\<lfc pri=\\"7\\" id=\\"rgendron02\\"\>15:44 [LFC] Rgendron02: Lord Giacomo is frozen, and has been disconnected.", "\<lfc pri=\\"7\\" id=\\"rgendron02\\"\>15:44 [LFC] Rgendron02: Lord Giacomo is frozen, and has been disconnected.", "\<lfc pri=\\"7\\" id=\\"rgendron02\\"\>15:44 [LFC] Rgendron02: Lord Giacomo is frozen, and has been disconnected.", "\<lfc pri=\\"7\\" id=\\"crond\\"\>00:00 [LFC] Crond: [Tue] Scheduled 11  executions [HD].", "\<lfc pri=\\"7\\" id=\\"crond\\"\>00:00 [LFC] Crond: [Wed] Scheduled 11  executions [HD].", "\<lfc pri=\\"7\\" id=\\"crond\\"\>00:00 [LFC] Crond: [Thu] Scheduled 11  executions [HD].", "\<lfc pri=\\"7\\" id=\\"crond\\"\>00:00 [LFC] Crond: [Fri] Scheduled 11  executions [HD].", "\<lfc pri=\\"7\\" id=\\"crond\\"\>00:00 [LFC] Crond: [Sat] Scheduled 11  executions [HD].", "\<lfc pri=\\"7\\" id=\\"asernova\\"\>14:20 [LFC] Asernova: Tomaso has been unfrozen.", "\<lfc pri=\\"7\\" id=\\"crond\\"\>00:00 [LFC] Crond: [Sun] Scheduled 14  executions [HDW].", "\<lfc pri=\\"7\\" id=\\"sharedcore\\"\>03:15 [LFC] SharedCore: Expanding shared folder; things might be laggy for a bit.", "\<lfc pri=\\"7\\" id=\\"jominey\\"\>21:14 [LFC] Jominey: Bruno has been unfrozen.", "\<lfc pri=\\"7\\" id=\\"jominey\\"\>23:25 [LFC] Jominey: Nicolas has been unfrozen.", "\<lfc pri=\\"7\\" id=\\"crond\\"\>00:00 [LFC] Crond: [Mon] Scheduled 11  executions [HD].", "\<lfc pri=\\"7\\" id=\\"jominey\\"\>21:12 [LFC] Jominey: StoryHost Roo has been unfrozen.", "\<lfc pri=\\"7\\" id=\\"crond\\"\>00:00 [LFC] Crond: [Tue] Scheduled 11  executions [HD]." \})
      </Core:Property>
      <Core:Property property="chat:layout-emote">
         "(time) [(chat)] (user): "
      </Core:Property>
      <Core:Property property="chat:layout-end"/>
      <Core:Property property="chat:layout-evoke">
         "(time) [(chat)] (user): "
      </Core:Property>
      <Core:Property property="chat:listeners">
         (\{ \<Chatters:AE:az:azrael\>, nil, \<[IronClaw:Staff:Karma:Bugs:Dragonfly]#99674\> \})
      </Core:Property>
      <Core:Property property="chat:name">"LFC"</Core:Property>
      <Core:Property property="chat:prefer">
         ([ "abiwan":"Bast", "arrianna":"Cake", "delfina":"StoryBuilder Karma", "idrocket":"Zazem", "missk":"StoryPlotter Eos", "morwenlorelie":"StoryBuilder Cersei", "orcsuit":"Splunks", "rorschakovacs":"StoryBuilder Guinness", "sanc_the_dark":"Sir Burcet", "tangerine":"Aurelius", "tunk_bodin":"Death" ])
      </Core:Property>
      <Core:Property property="chat:purpose">
         "Debug chan"
      </Core:Property>
      <Core:Property property="chat:style">"wc"</Core:Property>
      <Core:Property property="name">"LFC"</Core:Property>
      <Core:Property property="revisions">
         (\{ 1084063538, "zwoc", "E", 1084064168, "zwoc", "E" \})
      </Core:Property>
      <Core:Property property="skill:fatigue">1.0</Core:Property>
    </Core:Properties>
    <Notes:Notes/>
  </Base:Thing>
</object>
