<object clone="/usr/SkotOS/obj/verb" owner="Socials">
  <Socials:Verb imp="tilt" second="tilt" third="tilts" evoke="optional" audible="false" private="false" secret="false" obscured="false" target-abstracts="false" disabled="false" ooc="false" raw_verb="false">
    <Ur:UrObject/>
    <Socials:SocialObjects>
      <Socials:SocialObject role="dob" direct="true" single="false" raw="false" requirement="optional" distance="far">
        <Socials:SocObPreps/>
        <Socials:SocObFilters/>
      </Socials:SocialObject>
      <Socials:SocialObject role="iob" direct="false" single="false" raw="false" requirement="optional" distance="far">
        <Socials:SocObPreps>
          <Socials:SocObPrep prep="above"/>
          <Socials:SocObPrep prep="against"/>
          <Socials:SocObPrep prep="along"/>
          <Socials:SocObPrep prep="around"/>
          <Socials:SocObPrep prep="at"/>
          <Socials:SocObPrep prep="before"/>
          <Socials:SocObPrep prep="behind"/>
          <Socials:SocObPrep prep="below"/>
          <Socials:SocObPrep prep="beneath"/>
          <Socials:SocObPrep prep="beside"/>
          <Socials:SocObPrep prep="between"/>
          <Socials:SocObPrep prep="down"/>
          <Socials:SocObPrep prep="from"/>
          <Socials:SocObPrep prep="for"/>
          <Socials:SocObPrep prep="in"/>
          <Socials:SocObPrep prep="into"/>
          <Socials:SocObPrep prep="onto"/>
          <Socials:SocObPrep prep="on"/>
          <Socials:SocObPrep prep="over"/>
          <Socials:SocObPrep prep="to"/>
          <Socials:SocObPrep prep="near"/>
          <Socials:SocObPrep prep="toward"/>
          <Socials:SocObPrep prep="through"/>
          <Socials:SocObPrep prep="towards"/>
          <Socials:SocObPrep prep="under"/>
          <Socials:SocObPrep prep="up"/>
          <Socials:SocObPrep prep="upon"/>
          <Socials:SocObPrep prep="about"/>
          <Socials:SocObPrep prep="inside"/>
        </Socials:SocObPreps>
        <Socials:SocObFilters/>
      </Socials:SocialObject>
      <Socials:SocialObject role="iob-2" direct="false" single="false" raw="false" requirement="optional" distance="far">
        <Socials:SocObPreps>
          <Socials:SocObPrep prep="above"/>
          <Socials:SocObPrep prep="against"/>
          <Socials:SocObPrep prep="along"/>
          <Socials:SocObPrep prep="around"/>
          <Socials:SocObPrep prep="at"/>
          <Socials:SocObPrep prep="before"/>
          <Socials:SocObPrep prep="behind"/>
          <Socials:SocObPrep prep="below"/>
          <Socials:SocObPrep prep="beneath"/>
          <Socials:SocObPrep prep="beside"/>
          <Socials:SocObPrep prep="between"/>
          <Socials:SocObPrep prep="down"/>
          <Socials:SocObPrep prep="from"/>
          <Socials:SocObPrep prep="for"/>
          <Socials:SocObPrep prep="in"/>
          <Socials:SocObPrep prep="into"/>
          <Socials:SocObPrep prep="onto"/>
          <Socials:SocObPrep prep="on"/>
          <Socials:SocObPrep prep="over"/>
          <Socials:SocObPrep prep="to"/>
          <Socials:SocObPrep prep="near"/>
          <Socials:SocObPrep prep="toward"/>
          <Socials:SocObPrep prep="through"/>
          <Socials:SocObPrep prep="towards"/>
          <Socials:SocObPrep prep="under"/>
          <Socials:SocObPrep prep="up"/>
          <Socials:SocObPrep prep="upon"/>
        </Socials:SocObPreps>
        <Socials:SocObFilters/>
      </Socials:SocialObject>
      <Socials:SocialObject role="with" direct="false" single="false" raw="false" requirement="optional" distance="far">
        <Socials:SocObPreps>
          <Socials:SocObPrep prep="with"/>
        </Socials:SocObPreps>
        <Socials:SocObFilters/>
      </Socials:SocialObject>
    </Socials:SocialObjects>
    <Socials:VerbActions/>
    <Core:Properties>
      <Core:Property property="revisions">
         (\{ 1054998164, "sorcha", "E", 1054998296, "sorcha", "E", 1063131239, "sorcha", "E", 1084602787, "tangerine", "X", 1172898599, "sinvyrae", "E", 1172898622, "sinvyrae", "E", 1172909658, "???", "R", 1184316278, "sinvyrae", "E", 1184396966, "???", "R", 1191761200, "sinvyrae", "E", 1191827335, "???", "R", 1218951962, "meepy", "X", 1223120861, "???", "R", 1562080195, "sendnoodlez", "X", 1596393793, "sendnoodlez", "X" \})
      </Core:Property>
      <Core:Property property="sys:sync:clearing">0</Core:Property>
      <Core:Property property="sys:sync:idpsource">
         "ironclaw"
      </Core:Property>
      <Core:Property property="sys:sync:igdipro">
         "propose"
      </Core:Property>
      <Core:Property property="sys:sync:imported">
         1223120861
      </Core:Property>
      <Core:Property property="sys:sync:proposing-revision">
         1223120861
      </Core:Property>
    </Core:Properties>
    <Notes:Notes/>
  </Socials:Verb>
</object>
