<object clone="/base/obj/thing" owner="christophera">
  <Base:Thing>
    <Ur:UrObject/>
    <Base:Bulk immobile="false" mass="1" density="1"/>
    <Base:Container flexible="false" transparent-container="false" public-container="false" tight="false" capacity="1" maxweight="1"/>
    <Base:Misc gender="neuter" volition="false" weapon="false" default_stance="none" combinable="false" discrete="false" by_weight="false" tight="false" scriptrunner="false">
      <Base:Edible value="false"/>
      <Base:Potable value="false"/>
      <Base:DrinkMessageFirst/>
      <Base:DrinkMessageThird/>
      <Base:Transparency value="false"/>
      <Base:Unsafe value="false"/>
      <Base:Safe value="false"/>
      <Base:ClothesExpected value="false"/>
      <Base:DieMessageFirst/>
      <Base:DieMessageThird/>
    </Base:Misc>
    <Base:Details>
      <Base:Detail id="ceiling" prime="false" def="true" abstract="false" hidden="false" luminosity="0" targetable_in_dark="true" plural="false">
        <Base:Preposition close="false" against="false" under="false" on="false" inside="false" near="false" over="false" behind="false" before="false" beside="false"/>
        <Base:Names>
          <Base:SNames>
            <Base:SName sname="ceiling"/>
            <Base:SName sname="roof"/>
          </Base:SNames>
          <Base:PNames>
            <Base:PName pname="ceilings"/>
            <Base:PName pname="roofs"/>
          </Base:PNames>
        </Base:Names>
        <Base:Adjectives>
          <Base:Adjective adjective="oak"/>
          <Base:Adjective adjective="overhead"/>
          <Base:Adjective adjective="pale"/>
          <Base:Adjective adjective="white"/>
          <Base:Adjective adjective="white-painted"/>
          <Base:Adjective adjective="wood"/>
          <Base:Adjective adjective="wooden"/>
        </Base:Adjectives>
        <Base:Descriptions>
          <Base:Description type="brief">
             the ceiling
          </Base:Description>
          <Base:Description type="brief-dark">
             something overhead in the darkness
          </Base:Description>
          <Base:Description type="look-bright">
             A ceiling of white-painted boards covers this area. A light fixture is attached to it.<br/>--*look-bright in urroom*--
          </Base:Description>
          <Base:Description type="look-dark">
             There is apparently a ceiling somewhere overhead in this dark room.<br/>--*look-dark in urroom*--
          </Base:Description>
          <Base:Description type="look-dim">
             A ceiling of pale boards covers this dim area. An unlit light fixture is attached to it.<br/>--*look-dim in urroom*--
          </Base:Description>
          <Base:Description type="pbrief">
             the ceilings
          </Base:Description>
        </Base:Descriptions>
        <Base:Exit door="false" never_obvious="false" obvious_when_open="false" hidden_when_closed="false" separate="false" self-locking="false" deadbolt="false"/>
        <Base:Climbable/>
      </Base:Detail>
      <Base:Detail id="corner northeast" prime="false" def="true" abstract="false" hidden="false" luminosity="0" targetable_in_dark="true" plural="false">
        <Base:Preposition close="true" against="true" under="false" on="false" inside="true" near="true" over="false" behind="false" before="true" beside="true"/>
        <Base:Names>
          <Base:SNames>
            <Base:SName sname="corner"/>
            <Base:SName sname="angle"/>
          </Base:SNames>
          <Base:PNames>
            <Base:PName pname="angles"/>
            <Base:PName pname="corners"/>
          </Base:PNames>
        </Base:Names>
        <Base:Adjectives>
          <Base:Adjective adjective="area"/>
          <Base:Adjective adjective="northeast"/>
          <Base:Adjective adjective="northeastern"/>
          <Base:Adjective adjective="room"/>
        </Base:Adjectives>
        <Base:Descriptions>
          <Base:Description type="brief">
             the northeastern corner
          </Base:Description>
          <Base:Description type="brief-dark">
             the northeastern corner
          </Base:Description>
          <Base:Description type="look-bright">
             The northeastern corner of the room.<br/>--*look-bright in urroom*--
          </Base:Description>
          <Base:Description type="look-dark">
             The northeastern corner of a dark room.<br/>--*look-dark in urroom*--
          </Base:Description>
          <Base:Description type="look-dim">
             The northeastern corner of a dim room.<br/>--*look-dim in urroom*--
          </Base:Description>
          <Base:Description type="pbrief">
             the corners
          </Base:Description>
        </Base:Descriptions>
        <Base:Exit door="false" never_obvious="false" obvious_when_open="false" hidden_when_closed="false" separate="false" self-locking="false" deadbolt="false"/>
        <Base:Climbable/>
      </Base:Detail>
      <Base:Detail id="corner northwest" prime="false" def="true" abstract="false" hidden="false" luminosity="0" targetable_in_dark="true" plural="false">
        <Base:Preposition close="true" against="true" under="false" on="false" inside="true" near="true" over="false" behind="false" before="true" beside="true"/>
        <Base:Names>
          <Base:SNames>
            <Base:SName sname="corner"/>
            <Base:SName sname="angle"/>
          </Base:SNames>
          <Base:PNames>
            <Base:PName pname="angles"/>
            <Base:PName pname="corners"/>
          </Base:PNames>
        </Base:Names>
        <Base:Adjectives>
          <Base:Adjective adjective="area"/>
          <Base:Adjective adjective="northwest"/>
          <Base:Adjective adjective="northwestern"/>
          <Base:Adjective adjective="room"/>
        </Base:Adjectives>
        <Base:Descriptions>
          <Base:Description type="brief">
             the northwestern corner
          </Base:Description>
          <Base:Description type="brief-dark">
             the northwestern corner
          </Base:Description>
          <Base:Description type="look-bright">
             The northwestern corner of the room.<br/>--*look-bright in urroom*--
          </Base:Description>
          <Base:Description type="look-dark">
             The northwestern corner of a dark room.<br/>--*look-dark in urroom*--
          </Base:Description>
          <Base:Description type="look-dim">
             The northwestern corner of a dim room.<br/>--*look-dim in urroom*--
          </Base:Description>
          <Base:Description type="pbrief">
             the corners
          </Base:Description>
        </Base:Descriptions>
        <Base:Exit door="false" never_obvious="false" obvious_when_open="false" hidden_when_closed="false" separate="false" self-locking="false" deadbolt="false"/>
        <Base:Climbable/>
      </Base:Detail>
      <Base:Detail id="corner southeast" prime="false" def="true" abstract="false" hidden="false" luminosity="0" targetable_in_dark="true" plural="false">
        <Base:Preposition close="true" against="true" under="false" on="false" inside="true" near="true" over="false" behind="false" before="true" beside="true"/>
        <Base:Names>
          <Base:SNames>
            <Base:SName sname="corner"/>
            <Base:SName sname="angle"/>
          </Base:SNames>
          <Base:PNames>
            <Base:PName pname="angles"/>
            <Base:PName pname="corners"/>
          </Base:PNames>
        </Base:Names>
        <Base:Adjectives>
          <Base:Adjective adjective="area"/>
          <Base:Adjective adjective="room"/>
          <Base:Adjective adjective="southeast"/>
          <Base:Adjective adjective="southeastern"/>
        </Base:Adjectives>
        <Base:Descriptions>
          <Base:Description type="brief">
             the southeastern corner
          </Base:Description>
          <Base:Description type="brief-dark">
             the southeastern corner
          </Base:Description>
          <Base:Description type="look-bright">
             The southeastern corner of the room.<br/>--*look-bright in urroom*--
          </Base:Description>
          <Base:Description type="look-dark">
             The southeastern corner of a dark room.<br/>--*look-dark in urroom*--
          </Base:Description>
          <Base:Description type="look-dim">
             The southeastern corner of a dim room.<br/>--*look-dim in urroom*--
          </Base:Description>
          <Base:Description type="pbrief">
             the corners
          </Base:Description>
        </Base:Descriptions>
        <Base:Exit door="false" never_obvious="false" obvious_when_open="false" hidden_when_closed="false" separate="false" self-locking="false" deadbolt="false"/>
        <Base:Climbable/>
      </Base:Detail>
      <Base:Detail id="corner southwest" prime="false" def="true" abstract="false" hidden="false" luminosity="0" targetable_in_dark="true" plural="false">
        <Base:Preposition close="true" against="true" under="false" on="false" inside="true" near="true" over="false" behind="false" before="true" beside="true"/>
        <Base:Names>
          <Base:SNames>
            <Base:SName sname="corner"/>
            <Base:SName sname="angle"/>
          </Base:SNames>
          <Base:PNames>
            <Base:PName pname="angles"/>
            <Base:PName pname="corners"/>
          </Base:PNames>
        </Base:Names>
        <Base:Adjectives>
          <Base:Adjective adjective="area"/>
          <Base:Adjective adjective="room"/>
          <Base:Adjective adjective="southwest"/>
          <Base:Adjective adjective="southwestern"/>
        </Base:Adjectives>
        <Base:Descriptions>
          <Base:Description type="brief">
             the southwestern corner
          </Base:Description>
          <Base:Description type="brief-dark">
             the southwestern corner
          </Base:Description>
          <Base:Description type="look-bright">
             The southwestern corner of the room.<br/>--*look-bright in urroom*--
          </Base:Description>
          <Base:Description type="look-dark">
             The southwestern corner of a dark room.<br/>--*look-dark in urroom*--
          </Base:Description>
          <Base:Description type="look-dim">
             The southwestern corner of a dim room.<br/>--*look-dim in urroom*--
          </Base:Description>
          <Base:Description type="pbrief">
             the corners
          </Base:Description>
        </Base:Descriptions>
        <Base:Exit door="false" never_obvious="false" obvious_when_open="false" hidden_when_closed="false" separate="false" self-locking="false" deadbolt="false"/>
        <Base:Climbable/>
      </Base:Detail>
      <Base:Detail id="floor" prime="false" def="true" abstract="false" hidden="false" luminosity="0" targetable_in_dark="true" plural="false">
        <Base:Preposition close="true" against="false" under="false" on="true" inside="false" near="true" over="false" behind="false" before="false" beside="false"/>
        <Base:Names>
          <Base:SNames>
            <Base:SName sname="floor"/>
            <Base:SName sname="board"/>
            <Base:SName sname="ground"/>
          </Base:SNames>
          <Base:PNames>
            <Base:PName pname="boards"/>
            <Base:PName pname="floors"/>
            <Base:PName pname="grounds"/>
          </Base:PNames>
        </Base:Names>
        <Base:Adjectives>
          <Base:Adjective adjective="floor"/>
          <Base:Adjective adjective="oak"/>
          <Base:Adjective adjective="oaken"/>
          <Base:Adjective adjective="wood"/>
          <Base:Adjective adjective="wooden"/>
        </Base:Adjectives>
        <Base:Descriptions>
          <Base:Description type="brief">
             the floor
          </Base:Description>
          <Base:Description type="brief-dark">
             the floor
          </Base:Description>
          <Base:Description type="look-bright">
             A wooden floor.<br/>--*look-bright in urroom*--
          </Base:Description>
          <Base:Description type="look-dark">
             A wooden floor. <br/>--*look-dark in urroom*--
          </Base:Description>
          <Base:Description type="look-dim">
             The floor is made from wooden planks. <br/>--*look-dim in urroom*--
          </Base:Description>
          <Base:Description type="pbrief">
             the floors
          </Base:Description>
        </Base:Descriptions>
        <Base:Exit door="false" never_obvious="false" obvious_when_open="false" hidden_when_closed="false" separate="false" self-locking="false" deadbolt="false"/>
        <Base:Climbable/>
      </Base:Detail>
      <Base:Detail id="lamp" prime="false" def="false" abstract="false" hidden="false" luminosity="0" targetable_in_dark="false" plural="false">
        <Base:Preposition close="false" against="false" under="true" on="false" inside="false" near="false" over="false" behind="false" before="false" beside="false"/>
        <Base:Names>
          <Base:SNames>
            <Base:SName sname="lamp"/>
            <Base:SName sname="fixture"/>
            <Base:SName sname="light"/>
            <Base:SName sname="lighting"/>
            <Base:SName sname="glass"/>
            <Base:SName sname="dome"/>
            <Base:SName sname="band"/>
            <Base:SName sname="rim"/>
          </Base:SNames>
          <Base:PNames>
            <Base:PName pname="bands"/>
            <Base:PName pname="domes"/>
            <Base:PName pname="fixtures"/>
            <Base:PName pname="glasses"/>
            <Base:PName pname="lamps"/>
            <Base:PName pname="lights"/>
            <Base:PName pname="rims"/>
          </Base:PNames>
        </Base:Names>
        <Base:Adjectives>
          <Base:Adjective adjective="brass"/>
          <Base:Adjective adjective="ceiling"/>
          <Base:Adjective adjective="domed"/>
          <Base:Adjective adjective="frosted"/>
          <Base:Adjective adjective="glass"/>
          <Base:Adjective adjective="lamp"/>
          <Base:Adjective adjective="light"/>
          <Base:Adjective adjective="metal"/>
          <Base:Adjective adjective="simple"/>
        </Base:Adjectives>
        <Base:Descriptions>
          <Base:Description type="brief">
             ceiling lamp fixture
          </Base:Description>
          <Base:Description type="examine-bright">
             A simple lamp fixture is attached to the ceiling. It has a frosted glass dome of a milky white color{? | $(this.details:lamp:luminosity) |, glowing brightly, } and set in a brass band rim about fifteen inches in diameter.<br/>--*examine-bright in urroom*--
          </Base:Description>
          <Base:Description type="examine-dark">
             A dark lamp fixture is attached to the ceiling, set in a dark band rim about fifteen inches in diameter.<br/>--*examine-dark in urroom*--
          </Base:Description>
          <Base:Description type="examine-dim">
             A lamp fixture is attached to the ceiling. It is a simple dome, made up of a grayish-white glass, set in a band rim about fifteen inches in diameter. It is {? | $(this.details:lamp:luminosity) |glowing with light|unlit}. <br/>--*examine-dim in urroom*--
          </Base:Description>
          <Base:Description type="look-bright">
             A simple lamp fixture is attached to the ceiling. It is {? | $(this.details:lamp:luminosity) |glowing with a bright white light|unlit}. <br/>--*look-bright in urroom*--
          </Base:Description>
          <Base:Description type="look-dark">
             A unlit lamp fixture is attached to the ceiling.<br/>--*look-dark in urroom*--
          </Base:Description>
          <Base:Description type="look-dim">
             A simple dome lamp fixture is attached to the ceiling. It is {? | $(this.details:lamp:luminosity) |lit|unlit}.--*look-dim in urroom*--
          </Base:Description>
          <Base:Description type="pbrief">
             ceiling lamp fixtures
          </Base:Description>
          <Base:Description type="react-pre:sense/touch-dob">
             You can't quite reach the ceiling lamp fixture.<br/>--*react-pre:sense/touch-dob in urroom*--
          </Base:Description>
          <Base:Description type="react-pre:toggle-dob">
             There is nothing to toggle on the ceiling lamp. Maybe you want to toggle the switch?<br/>--*react-pre:toggle-dob in urroom*--
          </Base:Description>
        </Base:Descriptions>
        <Base:Exit door="false" never_obvious="false" obvious_when_open="false" hidden_when_closed="false" separate="false" self-locking="false" deadbolt="false"/>
        <Base:Climbable/>
      </Base:Detail>
      <Base:Detail id="light door" prime="false" def="false" abstract="false" hidden="false" luminosity="0" targetable_in_dark="false" plural="false">
        <Base:Preposition close="false" against="false" under="false" on="false" inside="false" near="false" over="false" behind="false" before="false" beside="false"/>
        <Base:Names>
          <Base:SNames>
            <Base:SName sname="light"/>
            <Base:SName sname="illumination"/>
          </Base:SNames>
          <Base:PNames>
            <Base:PName pname="illuminations"/>
            <Base:PName pname="lights"/>
          </Base:PNames>
        </Base:Names>
        <Base:Adjectives>
          <Base:Adjective adjective="dim"/>
          <Base:Adjective adjective="distant"/>
          <Base:Adjective adjective="door"/>
          <Base:Adjective adjective="faint"/>
          <Base:Adjective adjective="other"/>
        </Base:Adjectives>
        <Base:Descriptions>
          <Base:Description type="brief">
             light from the other side of the open door
          </Base:Description>
          <Base:Description type="look-bright">
             {? | $(this.details:lamp:luminosity) | Some|No} light shines from the other side of the open door.<br/>--*look-bright in urroom*--
          </Base:Description>
          <Base:Description type="look-dark">
             It is dark in here.<br/>--*look-dark in urroom*--
          </Base:Description>
          <Base:Description type="look-dim">
             {? | $(this.details:lamp:luminosity) | Some|No} light shines from the other side of the open door{? | $(this.details:lamp:luminosity) |, dimly illuminating <describe what="$(actor.base:environment)"/>}. <br/>--*look-dim in urroom*--
          </Base:Description>
        </Base:Descriptions>
        <Base:Exit door="false" never_obvious="false" obvious_when_open="false" hidden_when_closed="false" separate="false" self-locking="false" deadbolt="false"/>
        <Base:Climbable/>
      </Base:Detail>
      <Base:Detail id="lightcheck" prime="false" def="true" abstract="false" hidden="false" luminosity="0" targetable_in_dark="false" plural="false">
        <Base:Preposition close="false" against="false" under="false" on="false" inside="false" near="false" over="false" behind="false" before="false" beside="false"/>
        <Base:Names>
          <Base:SNames>
            <Base:SName sname="lights"/>
            <Base:SName sname="brightness"/>
          </Base:SNames>
          <Base:PNames>
            <Base:PName pname="brightnesses"/>
          </Base:PNames>
        </Base:Names>
        <Base:Adjectives>
          <Base:Adjective adjective="bright"/>
          <Base:Adjective adjective="dim"/>
        </Base:Adjectives>
        <Base:Descriptions>
          <Base:Description type="brief">lights</Base:Description>
          <Base:Description type="look-full">
             <describe what="$(this)" cap="1"/> is    $[Call(${Lib:light}, "lights-description", $env: $this)].<br/>--*look-full in urroom*--<br/>--*call SAM to give dynamic description in urroom*--
          </Base:Description>
          <Base:Description type="pbrief">lights</Base:Description>
        </Base:Descriptions>
        <Base:Exit door="false" never_obvious="false" obvious_when_open="false" hidden_when_closed="false" separate="false" self-locking="false" deadbolt="false"/>
        <Base:Climbable/>
      </Base:Detail>
      <Base:Detail id="middle" prime="false" def="true" abstract="false" hidden="false" luminosity="0" targetable_in_dark="true" plural="false">
        <Base:Preposition close="true" against="false" under="false" on="true" inside="true" near="true" over="false" behind="false" before="true" beside="true"/>
        <Base:Names>
          <Base:SNames>
            <Base:SName sname="middle"/>
            <Base:SName sname="center"/>
          </Base:SNames>
          <Base:PNames>
            <Base:PName pname="centers"/>
            <Base:PName pname="middles"/>
          </Base:PNames>
        </Base:Names>
        <Base:Adjectives>
          <Base:Adjective adjective="area"/>
          <Base:Adjective adjective="floor"/>
          <Base:Adjective adjective="room"/>
        </Base:Adjectives>
        <Base:Descriptions>
          <Base:Description type="brief">
             the middle of the room
          </Base:Description>
          <Base:Description type="brief-dark">
             the middle of the room
          </Base:Description>
          <Base:Description type="look-bright">
             The middle of the room.<br/>--*look-bright in urroom*--
          </Base:Description>
          <Base:Description type="look-dark">
             The middle of a dark room.<br/>--*look-dark in urroom*--
          </Base:Description>
          <Base:Description type="look-dim">
             The middle of a dim room.<br/>--*look-dim in urroom*--
          </Base:Description>
        </Base:Descriptions>
        <Base:Exit door="false" never_obvious="false" obvious_when_open="false" hidden_when_closed="false" separate="false" self-locking="false" deadbolt="false"/>
        <Base:Climbable/>
      </Base:Detail>
      <Base:Detail id="wall east" prime="false" def="true" abstract="false" hidden="false" luminosity="0" targetable_in_dark="true" plural="false">
        <Base:Preposition close="true" against="true" under="false" on="false" inside="false" near="true" over="false" behind="false" before="true" beside="true"/>
        <Base:Names>
          <Base:SNames>
            <Base:SName sname="wall"/>
            <Base:SName sname="side"/>
            <Base:SName sname="board"/>
          </Base:SNames>
          <Base:PNames>
            <Base:PName pname="boards"/>
            <Base:PName pname="sides"/>
            <Base:PName pname="walls"/>
          </Base:PNames>
        </Base:Names>
        <Base:Adjectives>
          <Base:Adjective adjective="east"/>
          <Base:Adjective adjective="eastern"/>
          <Base:Adjective adjective="oak"/>
          <Base:Adjective adjective="painted"/>
          <Base:Adjective adjective="pale"/>
          <Base:Adjective adjective="side"/>
          <Base:Adjective adjective="white"/>
          <Base:Adjective adjective="white-painted"/>
          <Base:Adjective adjective="wood"/>
          <Base:Adjective adjective="wooden"/>
        </Base:Adjectives>
        <Base:Descriptions>
          <Base:Description type="brief">
             the eastern wall
          </Base:Description>
          <Base:Description type="brief-dark">
             the east side of the room
          </Base:Description>
          <Base:Description type="look-bright">
             White-painted wooden boards form the eastern wall.<br/>--*look-bright in urroom*--
          </Base:Description>
          <Base:Description type="look-dark">
             The eastern wall of this dark room is made of wood.<br/>--*look-dark in urroom*--
          </Base:Description>
          <Base:Description type="look-dim">
             A pale wooden wall to the east.<br/>--*look-dim in urroom*--
          </Base:Description>
          <Base:Description type="pbrief">
             the walls
          </Base:Description>
        </Base:Descriptions>
        <Base:Exit door="false" never_obvious="false" obvious_when_open="false" hidden_when_closed="false" separate="false" self-locking="false" deadbolt="false"/>
        <Base:Climbable/>
      </Base:Detail>
      <Base:Detail id="wall north" prime="false" def="true" abstract="false" hidden="false" luminosity="0" targetable_in_dark="true" plural="false">
        <Base:Preposition close="true" against="true" under="false" on="false" inside="false" near="true" over="false" behind="false" before="true" beside="true"/>
        <Base:Names>
          <Base:SNames>
            <Base:SName sname="wall"/>
            <Base:SName sname="side"/>
            <Base:SName sname="board"/>
          </Base:SNames>
          <Base:PNames>
            <Base:PName pname="boards"/>
            <Base:PName pname="sides"/>
            <Base:PName pname="walls"/>
          </Base:PNames>
        </Base:Names>
        <Base:Adjectives>
          <Base:Adjective adjective="north"/>
          <Base:Adjective adjective="northern"/>
          <Base:Adjective adjective="oak"/>
          <Base:Adjective adjective="painted"/>
          <Base:Adjective adjective="pale"/>
          <Base:Adjective adjective="side"/>
          <Base:Adjective adjective="white"/>
          <Base:Adjective adjective="white-painted"/>
          <Base:Adjective adjective="wood"/>
          <Base:Adjective adjective="wooden"/>
        </Base:Adjectives>
        <Base:Descriptions>
          <Base:Description type="brief">
             the northern wall
          </Base:Description>
          <Base:Description type="brief-dark">
             the north side of the room
          </Base:Description>
          <Base:Description type="look-bright">
             White-painted wooden boards form the northern wall.<br/>--*look-bright in urroom*--
          </Base:Description>
          <Base:Description type="look-dark">
             The northern wall of this dark room is made of wood.<br/>--*look-dark in urroom*--
          </Base:Description>
          <Base:Description type="look-dim">
             A pale wooden wall to the north.<br/>--*look-dim in urroom*--
          </Base:Description>
          <Base:Description type="pbrief">
             the walls
          </Base:Description>
        </Base:Descriptions>
        <Base:Exit door="false" never_obvious="false" obvious_when_open="false" hidden_when_closed="false" separate="false" self-locking="false" deadbolt="false"/>
        <Base:Climbable/>
      </Base:Detail>
      <Base:Detail id="wall south" prime="false" def="true" abstract="false" hidden="false" luminosity="0" targetable_in_dark="true" plural="false">
        <Base:Preposition close="true" against="true" under="false" on="false" inside="false" near="true" over="false" behind="false" before="true" beside="true"/>
        <Base:Names>
          <Base:SNames>
            <Base:SName sname="wall"/>
            <Base:SName sname="side"/>
            <Base:SName sname="board"/>
          </Base:SNames>
          <Base:PNames>
            <Base:PName pname="boards"/>
            <Base:PName pname="sides"/>
            <Base:PName pname="walls"/>
          </Base:PNames>
        </Base:Names>
        <Base:Adjectives>
          <Base:Adjective adjective="oak"/>
          <Base:Adjective adjective="painted"/>
          <Base:Adjective adjective="pale"/>
          <Base:Adjective adjective="side"/>
          <Base:Adjective adjective="south"/>
          <Base:Adjective adjective="southern"/>
          <Base:Adjective adjective="white"/>
          <Base:Adjective adjective="white-painted"/>
          <Base:Adjective adjective="wood"/>
          <Base:Adjective adjective="wooden"/>
        </Base:Adjectives>
        <Base:Descriptions>
          <Base:Description type="brief">
             the southern wall
          </Base:Description>
          <Base:Description type="brief-dark">
             the south side of the room
          </Base:Description>
          <Base:Description type="look-bright">
             White-painted wooden boards form the southern wall.<br/>--*look-bright in urroom*--
          </Base:Description>
          <Base:Description type="look-dark">
             The southern wall of this dark room is made of wood.<br/>--*look-dark in urroom*--
          </Base:Description>
          <Base:Description type="look-dim">
             A pale wooden wall to the south.<br/>--*look-dim in urroom*--
          </Base:Description>
          <Base:Description type="pbrief">
             the walls
          </Base:Description>
        </Base:Descriptions>
        <Base:Exit door="false" never_obvious="false" obvious_when_open="false" hidden_when_closed="false" separate="false" self-locking="false" deadbolt="false"/>
        <Base:Climbable/>
      </Base:Detail>
      <Base:Detail id="wall west" prime="false" def="true" abstract="false" hidden="false" luminosity="0" targetable_in_dark="true" plural="false">
        <Base:Preposition close="true" against="true" under="false" on="false" inside="false" near="true" over="false" behind="false" before="true" beside="true"/>
        <Base:Names>
          <Base:SNames>
            <Base:SName sname="wall"/>
            <Base:SName sname="side"/>
            <Base:SName sname="board"/>
          </Base:SNames>
          <Base:PNames>
            <Base:PName pname="boards"/>
            <Base:PName pname="sides"/>
            <Base:PName pname="walls"/>
          </Base:PNames>
        </Base:Names>
        <Base:Adjectives>
          <Base:Adjective adjective="oak"/>
          <Base:Adjective adjective="painted"/>
          <Base:Adjective adjective="pale"/>
          <Base:Adjective adjective="side"/>
          <Base:Adjective adjective="west"/>
          <Base:Adjective adjective="western"/>
          <Base:Adjective adjective="white"/>
          <Base:Adjective adjective="white-painted"/>
          <Base:Adjective adjective="wood"/>
          <Base:Adjective adjective="wooden"/>
        </Base:Adjectives>
        <Base:Descriptions>
          <Base:Description type="brief">
             the western wall
          </Base:Description>
          <Base:Description type="brief-dark">
             the west side of the room
          </Base:Description>
          <Base:Description type="look-bright">
             White-painted wooden boards form the western wall.<br/>--*look-bright in urroom*--
          </Base:Description>
          <Base:Description type="look-dark">
             The western wall of this dark room is made of wood.<br/>--*look-dark in urroom*--
          </Base:Description>
          <Base:Description type="look-dim">
             A pale wooden wall to the west.<br/>--*look-dim in urroom*--
          </Base:Description>
          <Base:Description type="pbrief">
             the walls
          </Base:Description>
        </Base:Descriptions>
        <Base:Exit door="false" never_obvious="false" obvious_when_open="false" hidden_when_closed="false" separate="false" self-locking="false" deadbolt="false"/>
        <Base:Climbable/>
      </Base:Detail>
      <Base:Detail id="walls plural" prime="false" def="true" abstract="false" hidden="false" luminosity="0" targetable_in_dark="true" plural="false">
        <Base:Preposition close="false" against="false" under="false" on="false" inside="false" near="false" over="false" behind="false" before="false" beside="false"/>
        <Base:Names>
          <Base:SNames>
            <Base:SName sname="walls"/>
            <Base:SName sname="boards"/>
            <Base:SName sname="panels"/>
            <Base:SName sname="sides"/>
          </Base:SNames>
          <Base:PNames/>
        </Base:Names>
        <Base:Adjectives>
          <Base:Adjective adjective="all"/>
          <Base:Adjective adjective="oak"/>
          <Base:Adjective adjective="painted"/>
          <Base:Adjective adjective="pale"/>
          <Base:Adjective adjective="side"/>
          <Base:Adjective adjective="white"/>
          <Base:Adjective adjective="white-painted"/>
          <Base:Adjective adjective="wood"/>
          <Base:Adjective adjective="wooden"/>
        </Base:Adjectives>
        <Base:Descriptions>
          <Base:Description type="brief">
             the walls
          </Base:Description>
          <Base:Description type="brief-dark">
             the sides of the room
          </Base:Description>
          <Base:Description type="look-bright">
             White-painted wooden boards form the walls. <br/>--*look-bright in urroom*--
          </Base:Description>
          <Base:Description type="look-dark">
             The walls of this dark area are made of wood.<br/>--*look-dark in urroom*--
          </Base:Description>
          <Base:Description type="look-dim">
             Pale wooden walls surround this area.<br/>--*look-dim in urroom*--
          </Base:Description>
        </Base:Descriptions>
        <Base:Exit door="false" never_obvious="false" obvious_when_open="false" hidden_when_closed="false" separate="false" self-locking="false" deadbolt="false"/>
        <Base:Climbable/>
      </Base:Detail>
    </Base:Details>
    <Base:Combat>
      <Base:Strength value="1"/>
      <Base:MaxFatigue value="1"/>
    </Base:Combat>
    <Base:Clothing>
      <Base:SingleWear value="false"/>
    </Base:Clothing>
    <Base:Crafting see_level="0" do_level="0" time="0" attention="false" held="false">
      <Base:Ingredients/>
      <Base:Tools/>
      <Base:CraftVerbs/>
    </Base:Crafting>
    <Base:InitialContents/>
    <Base:InitialProperties/>
    <Core:Properties>
      <Core:Property property="revisions">
         (\{ 1050024203, "christophera", "X", 1050024277, "christophera", "E", 1050025088, "christophera", "K", 1050034989, "michaelb", "X", 1050097210, "christophera", "E", 1050098666, "christophera", "E", 1050363251, "christophera", "K", 1050363329, "christophera", "K", 1050364873, "michaelb", "X", 1050367621, "michaelb", "X", 1050374114, "christophera", "E", 1050374153, "christophera", "E", 1050374366, "christophera", "K", 1050374903, "christophera", "K", 1050375008, "christophera", "K", 1050375071, "christophera", "K", 1050376499, "christophera", "E", 1050377854, "christophera", "K", 1050378362, "christophera", "E", 1050378399, "christophera", "E", 1050378580, "christophera", "E", 1050378608, "christophera", "E", 1050378915, "christophera", "E", 1052265600, "michaelb", "X", 1052265996, "michaelb", "E", 1052266026, "michaelb", "X", 1052266256, "michaelb", "E", 1052266278, "michaelb", "X", 1052266329, "michaelb", "X", 1052266391, "michaelb", "X", 1052266665, "michaelb", "X" \})
      </Core:Property>
      <Core:Property property="skill:fatigue">1.0</Core:Property>
    </Core:Properties>
    <Notes:Notes/>
  </Base:Thing>
</object>
